memdb/__init__.py
memdb/dataset.py
memdb-0.0.5.dist-info/LICENSE
memdb-0.0.5.dist-info/METADATA
memdb-0.0.5.dist-info/WHEEL
memdb-0.0.5.dist-info/top_level.txt
memdb-0.0.5.dist-info/RECORD
