Metadata-Version: 2.1
Name: memdb
Version: 0.0.5
Summary: An in-memory agnostic database for Python.
Home-page: https://github.com/samuelcorradi/memdb
Author: Samuel Corradi
Author-email: samuelcorradi@gmail.com
Classifier: Programming Language :: Python :: 3
Classifier: License :: OSI Approved :: Apache Software License
Classifier: Operating System :: OS Independent
Classifier: Topic :: Database
Requires-Python: >=3.7.1
License-File: LICENSE
